gitignoregh/__init__.py
gitignoregh/__main__.py
gitignoregh/cli.py
gitignoregh/gitignoregh.py
gitignoregh-1.2.1.dist-info/METADATA
gitignoregh-1.2.1.dist-info/WHEEL
gitignoregh-1.2.1.dist-info/entry_points.txt
gitignoregh-1.2.1.dist-info/licenses/LICENSE
gitignoregh-1.2.1.dist-info/RECORD
