Metadata-Version: 2.4
Name: gitignoregh
Version: 1.2.1
Summary: gitignoregh is a command line tool that generates a .gitignore file for a project from the github gitignore templates repository
License: MIT
License-File: LICENSE
Keywords: gitignore,gitignoregh
Author: Saúl Piña
Author-email: sauljabin@gmail.com
Requires-Python: >=3.10,<3.15
Classifier: License :: OSI Approved :: MIT License
Classifier: Environment :: Console
Classifier: Operating System :: MacOS
Classifier: Operating System :: Unix
Classifier: Programming Language :: Python :: 3.10
Classifier: Programming Language :: Python :: 3.11
Classifier: Programming Language :: Python :: 3.12
Classifier: Programming Language :: Python :: 3.13
Classifier: Programming Language :: Python :: 3.14
Requires-Dist: click (>=8)
Requires-Dist: gitpython (>=3)
Requires-Dist: rich (>=14)
Project-URL: Homepage, https://github.com/sauljabin/gitignoregh
Project-URL: Repository, https://github.com/sauljabin/gitignoregh
